langspeak.py
book/__init__.py
book/mybook.py
laoqiproject-0.0.6.dist-info/LICENSE
laoqiproject-0.0.6.dist-info/METADATA
laoqiproject-0.0.6.dist-info/WHEEL
laoqiproject-0.0.6.dist-info/top_level.txt
laoqiproject-0.0.6.dist-info/RECORD
