Metadata-Version: 2.1
Name: laoqiproject
Version: 0.0.6
Summary: this is my first project.
Home-page: UNKNOWN
Author: qiwsir
Author-email: qiwsir@qq.com
License: UNKNOWN
Platform: UNKNOWN
Classifier: Programming Language :: Python :: 3
Classifier: License :: OSI Approved :: MIT License
Classifier: Operating System :: OS Independent
Requires-Python: >=3.6
